MANIFEST.in
README.md
setup.py
holster/__init__.py
holster/emitter.py
holster/enum.py
holster/errors.py
holster/filters.py
holster/flask_ext.py
holster/interface.py
holster/log.py
holster/responses.py
holster/scheduler.py
holster/session.py
holster/tasks.py
holster/threadlocal.py
holster/tokens.py
holster/util.py
holster.egg-info/PKG-INFO
holster.egg-info/SOURCES.txt
holster.egg-info/dependency_links.txt
holster.egg-info/not-zip-safe
holster.egg-info/requires.txt
holster.egg-info/top_level.txt