Metadata-Version: 1.0
Name: holster
Version: 2.0.0
Summary: a set of Python utilities
Home-page: https://github.com/b1naryth1ef/holster
Author: Andrei
Author-email: andrei.zbikowski@gmail.com
License: Apache 2.0
Platform: UNKNOWN
